kbomodels/__init__.py
kbomodels/kbomodels.py
kbomodels-2025.1.0.dist-info/METADATA
kbomodels-2025.1.0.dist-info/WHEEL
kbomodels-2025.1.0.dist-info/top_level.txt
kbomodels-2025.1.0.dist-info/RECORD
