Metadata-Version: 2.4
Name: kbomodels
Version: 2025.1.0
Summary: A Python package for Kabirian-based optinalysis (KBO) and other advanced estimations
Author: Abdullahi Kabir Bindawa
Author-email: ka.bindawa@gmail.com; kabir.abdullahi.ng@gmail.com
Classifier: Programming Language :: Python :: 3
Classifier: License :: OSI Approved :: MIT License
Classifier: Operating System :: OS Independent
Requires-Python: >=3.11
Requires-Dist: numpy
Dynamic: author
Dynamic: author-email
Dynamic: classifier
Dynamic: description
Dynamic: description-content-type
Dynamic: requires-dist
Dynamic: requires-python
Dynamic: summary
